{
    "author": "MonoGame Team",
    "classifications": [
        "MonoGame"
    ],
    "name": "MonoGame Windows Desktop Application (Windows DirectX)",
    "groupIdentity": "MonoGame.Application.WindowsDX",
    "identity": "MonoGame.Application.WindowsDX.CSharp",
    "shortName": "mgwindowsdx",
    "tags": {
        "language": "C#",
        "type": "project"
    },
    "primaryOutputs": [
        {
            "path": "MGNamespace.csproj"
        }
    ],
    "sourceName": "MGNamespace",
    "preferNameDirectory": "true",
    "description": "A MonoGame game project for Windows using DirectX.",
    "symbols": {
        "framework": {
            "type": "parameter",
            "defaultValue": "net5.0-windows",
            "replaces": "net5.0-windows"
        }
    }
}
